{"date":"2025-10-17","stage":"System Check","stageKey":"stage-0@0.1","seed":"1tqi2sz","roundSeeds":["19xltb2","u4fzlg","ip5e2k","o04u1f","1iaqsz7","3fyz0i","11xpyso","h3jjm","111n2ri","1slixpf","1vv0wgb","w2u8o6","1099uvp","1y8m119","1jcgere","29h43i","8i2hau","11c7g4a","v66sd9","10zbiuh"],"entries":[{"id":193,"score":205102,"gu":96.1645,"fc":100,"git":"f44dd55","rounds":[{"s":11695,"gu":97.45,"fc":100,"t":[0,0]},{"s":9933,"gu":97.38,"fc":100,"t":[0,0]},{"s":10822,"gu":97.49,"fc":100,"t":[0,0]},{"s":10211,"gu":97.24,"fc":100,"t":[0,0]},{"s":10814,"gu":97.42,"fc":100,"t":[0,0]},{"s":7850,"gu":96.91,"fc":100,"t":[0,0]},{"s":9612,"gu":97.09,"fc":100,"t":[0,0]},{"s":9389,"gu":97.8,"fc":100,"t":[0,0]},{"s":10823,"gu":94.93,"fc":100,"t":[0,0]},{"s":10771,"gu":94.48,"fc":100,"t":[0,0]},{"s":9980,"gu":95.04,"fc":100,"t":[0,0]},{"s":9610,"gu":94.21,"fc":100,"t":[0,0]},{"s":10817,"gu":97.45,"fc":100,"t":[0,0]},{"s":12259,"gu":97.29,"fc":100,"t":[0,0]},{"s":8738,"gu":97.08,"fc":100,"t":[0,0]},{"s":9364,"gu":94.58,"fc":100,"t":[0,0]},{"s":10844,"gu":95.12,"fc":100,"t":[0,0]},{"s":9642,"gu":94.52,"fc":100,"t":[0,0]},{"s":11983,"gu":95.1,"fc":100,"t":[0,0]},{"s":9945,"gu":94.71,"fc":100,"t":[0,0]}]},{"id":205,"score":205102,"gu":96.1645,"fc":100,"git":"f44dd55","rounds":[{"s":11695,"gu":97.45,"fc":100,"t":[0,0]},{"s":9933,"gu":97.38,"fc":100,"t":[0,0]},{"s":10822,"gu":97.49,"fc":100,"t":[0,0]},{"s":10211,"gu":97.24,"fc":100,"t":[0,0]},{"s":10814,"gu":97.42,"fc":100,"t":[0,0]},{"s":7850,"gu":96.91,"fc":100,"t":[0,0]},{"s":9612,"gu":97.09,"fc":100,"t":[0,0]},{"s":9389,"gu":97.8,"fc":100,"t":[0,0]},{"s":10823,"gu":94.93,"fc":100,"t":[0,0]},{"s":10771,"gu":94.48,"fc":100,"t":[0,0]},{"s":9980,"gu":95.04,"fc":100,"t":[0,0]},{"s":9610,"gu":94.21,"fc":100,"t":[0,0]},{"s":10817,"gu":97.45,"fc":100,"t":[0,0]},{"s":12259,"gu":97.29,"fc":100,"t":[0,0]},{"s":8738,"gu":97.08,"fc":100,"t":[0,0]},{"s":9364,"gu":94.58,"fc":100,"t":[0,0]},{"s":10844,"gu":95.12,"fc":100,"t":[0,0]},{"s":9642,"gu":94.52,"fc":100,"t":[0,0]},{"s":11983,"gu":95.1,"fc":100,"t":[0,0]},{"s":9945,"gu":94.71,"fc":100,"t":[0,0]}]},{"id":2,"score":205102,"gu":96.1645,"fc":100,"git":"f44dd55","rounds":[{"s":11695,"gu":97.45,"fc":100,"t":[0,0]},{"s":9933,"gu":97.38,"fc":100,"t":[0,0]},{"s":10822,"gu":97.49,"fc":100,"t":[0,0]},{"s":10211,"gu":97.24,"fc":100,"t":[0,0]},{"s":10814,"gu":97.42,"fc":100,"t":[0,0]},{"s":7850,"gu":96.91,"fc":100,"t":[0,0]},{"s":9612,"gu":97.09,"fc":100,"t":[0,0]},{"s":9389,"gu":97.8,"fc":100,"t":[0,0]},{"s":10823,"gu":94.93,"fc":100,"t":[0,0]},{"s":10771,"gu":94.48,"fc":100,"t":[0,0]},{"s":9980,"gu":95.04,"fc":100,"t":[0,0]},{"s":9610,"gu":94.21,"fc":100,"t":[0,0]},{"s":10817,"gu":97.45,"fc":100,"t":[0,0]},{"s":12259,"gu":97.29,"fc":100,"t":[0,0]},{"s":8738,"gu":97.08,"fc":100,"t":[0,0]},{"s":9364,"gu":94.58,"fc":100,"t":[0,0]},{"s":10844,"gu":95.12,"fc":100,"t":[0,0]},{"s":9642,"gu":94.52,"fc":100,"t":[0,0]},{"s":11983,"gu":95.1,"fc":100,"t":[0,0]},{"s":9945,"gu":94.71,"fc":100,"t":[0,0]}]},{"id":37,"score":205102,"gu":96.1645,"fc":100,"git":"f44dd55","rounds":[{"s":11695,"gu":97.45,"fc":100,"t":[0,0]},{"s":9933,"gu":97.38,"fc":100,"t":[0,0]},{"s":10822,"gu":97.49,"fc":100,"t":[0,0]},{"s":10211,"gu":97.24,"fc":100,"t":[0,0]},{"s":10814,"gu":97.42,"fc":100,"t":[0,0]},{"s":7850,"gu":96.91,"fc":100,"t":[0,0]},{"s":9612,"gu":97.09,"fc":100,"t":[0,0]},{"s":9389,"gu":97.8,"fc":100,"t":[0,0]},{"s":10823,"gu":94.93,"fc":100,"t":[0,0]},{"s":10771,"gu":94.48,"fc":100,"t":[0,0]},{"s":9980,"gu":95.04,"fc":100,"t":[0,0]},{"s":9610,"gu":94.21,"fc":100,"t":[0,0]},{"s":10817,"gu":97.45,"fc":100,"t":[0,0]},{"s":12259,"gu":97.29,"fc":100,"t":[0,0]},{"s":8738,"gu":97.08,"fc":100,"t":[0,0]},{"s":9364,"gu":94.58,"fc":100,"t":[0,0]},{"s":10844,"gu":95.12,"fc":100,"t":[0,0]},{"s":9642,"gu":94.52,"fc":100,"t":[0,0]},{"s":11983,"gu":95.1,"fc":100,"t":[0,0]},{"s":9945,"gu":94.71,"fc":100,"t":[0,0]}]},{"id":275,"score":205093,"gu":96.16,"fc":100,"git":"f44dd55","rounds":[{"s":11693,"gu":97.44,"fc":100,"t":[0,0]},{"s":9931,"gu":97.36,"fc":100,"t":[0,0]},{"s":10820,"gu":97.47,"fc":100,"t":[0,0]},{"s":10213,"gu":97.26,"fc":100,"t":[0,0]},{"s":10814,"gu":97.42,"fc":100,"t":[0,0]},{"s":7848,"gu":96.88,"fc":100,"t":[0,0]},{"s":9609,"gu":97.06,"fc":100,"t":[0,0]},{"s":9389,"gu":97.8,"fc":100,"t":[0,0]},{"s":10827,"gu":94.97,"fc":100,"t":[0,0]},{"s":10775,"gu":94.51,"fc":100,"t":[0,0]},{"s":9973,"gu":94.98,"fc":100,"t":[0,0]},{"s":9610,"gu":94.21,"fc":100,"t":[0,0]},{"s":10816,"gu":97.44,"fc":100,"t":[0,0]},{"s":12257,"gu":97.27,"fc":100,"t":[0,0]},{"s":8738,"gu":97.08,"fc":100,"t":[0,0]},{"s":9366,"gu":94.6,"fc":100,"t":[0,0]},{"s":10844,"gu":95.12,"fc":100,"t":[0,0]},{"s":9642,"gu":94.52,"fc":100,"t":[0,0]},{"s":11983,"gu":95.1,"fc":100,"t":[0,0]},{"s":9945,"gu":94.71,"fc":100,"t":[0,0]}]},{"id":256,"score":205087,"gu":96.15599999999999,"fc":100,"git":"f44dd55","rounds":[{"s":11696,"gu":97.46,"fc":100,"t":[0,0]},{"s":9948,"gu":97.52,"fc":100,"t":[0,0]},{"s":10823,"gu":97.5,"fc":100,"t":[0,0]},{"s":10213,"gu":97.26,"fc":100,"t":[0,0]},{"s":10818,"gu":97.45,"fc":100,"t":[0,0]},{"s":7832,"gu":96.69,"fc":100,"t":[0,0]},{"s":9591,"gu":96.87,"fc":100,"t":[0,0]},{"s":9387,"gu":97.78,"fc":100,"t":[0,0]},{"s":10826,"gu":94.96,"fc":100,"t":[0,0]},{"s":10775,"gu":94.51,"fc":100,"t":[0,0]},{"s":9968,"gu":94.93,"fc":100,"t":[0,0]},{"s":9597,"gu":94.08,"fc":100,"t":[0,0]},{"s":10531,"gu":97.5,"fc":100,"t":[0,0]},{"s":12257,"gu":97.27,"fc":100,"t":[0,0]},{"s":8734,"gu":97.04,"fc":100,"t":[0,0]},{"s":9375,"gu":94.69,"fc":100,"t":[0,0]},{"s":10850,"gu":95.17,"fc":100,"t":[0,0]},{"s":9642,"gu":94.52,"fc":100,"t":[0,0]},{"s":11982,"gu":95.09,"fc":100,"t":[0,0]},{"s":10242,"gu":94.83,"fc":100,"t":[0,0]}]},{"id":294,"score":205073,"gu":96.1505,"fc":100,"git":"f44dd55","rounds":[{"s":11687,"gu":97.39,"fc":100,"t":[0,0]},{"s":9931,"gu":97.36,"fc":100,"t":[0,0]},{"s":10818,"gu":97.45,"fc":100,"t":[0,0]},{"s":10215,"gu":97.28,"fc":100,"t":[0,0]},{"s":10814,"gu":97.42,"fc":100,"t":[0,0]},{"s":7848,"gu":96.88,"fc":100,"t":[0,0]},{"s":9608,"gu":97.05,"fc":100,"t":[0,0]},{"s":9389,"gu":97.8,"fc":100,"t":[0,0]},{"s":10825,"gu":94.95,"fc":100,"t":[0,0]},{"s":10775,"gu":94.51,"fc":100,"t":[0,0]},{"s":9969,"gu":94.94,"fc":100,"t":[0,0]},{"s":9608,"gu":94.19,"fc":100,"t":[0,0]},{"s":10816,"gu":97.44,"fc":100,"t":[0,0]},{"s":12259,"gu":97.29,"fc":100,"t":[0,0]},{"s":8734,"gu":97.04,"fc":100,"t":[0,0]},{"s":9366,"gu":94.6,"fc":100,"t":[0,0]},{"s":10842,"gu":95.1,"fc":100,"t":[0,0]},{"s":9644,"gu":94.54,"fc":100,"t":[0,0]},{"s":11981,"gu":95.08,"fc":100,"t":[0,0]},{"s":9944,"gu":94.7,"fc":100,"t":[0,0]}]},{"id":195,"score":205073,"gu":96.1505,"fc":100,"git":"f44dd55","rounds":[{"s":11687,"gu":97.39,"fc":100,"t":[0,0]},{"s":9931,"gu":97.36,"fc":100,"t":[0,0]},{"s":10818,"gu":97.45,"fc":100,"t":[0,0]},{"s":10215,"gu":97.28,"fc":100,"t":[0,0]},{"s":10814,"gu":97.42,"fc":100,"t":[0,0]},{"s":7848,"gu":96.88,"fc":100,"t":[0,0]},{"s":9608,"gu":97.05,"fc":100,"t":[0,0]},{"s":9389,"gu":97.8,"fc":100,"t":[0,0]},{"s":10825,"gu":94.95,"fc":100,"t":[0,0]},{"s":10775,"gu":94.51,"fc":100,"t":[0,0]},{"s":9969,"gu":94.94,"fc":100,"t":[0,0]},{"s":9608,"gu":94.19,"fc":100,"t":[0,0]},{"s":10816,"gu":97.44,"fc":100,"t":[0,0]},{"s":12259,"gu":97.29,"fc":100,"t":[0,0]},{"s":8734,"gu":97.04,"fc":100,"t":[0,0]},{"s":9366,"gu":94.6,"fc":100,"t":[0,0]},{"s":10842,"gu":95.1,"fc":100,"t":[0,0]},{"s":9644,"gu":94.54,"fc":100,"t":[0,0]},{"s":11981,"gu":95.08,"fc":100,"t":[0,0]},{"s":9944,"gu":94.7,"fc":100,"t":[0,0]}]},{"id":331,"score":205073,"gu":96.1505,"fc":100,"git":"f44dd55","rounds":[{"s":11687,"gu":97.39,"fc":100,"t":[0,0]},{"s":9931,"gu":97.36,"fc":100,"t":[0,0]},{"s":10818,"gu":97.45,"fc":100,"t":[0,0]},{"s":10215,"gu":97.28,"fc":100,"t":[0,0]},{"s":10814,"gu":97.42,"fc":100,"t":[0,0]},{"s":7848,"gu":96.88,"fc":100,"t":[0,0]},{"s":9608,"gu":97.05,"fc":100,"t":[0,0]},{"s":9389,"gu":97.8,"fc":100,"t":[0,0]},{"s":10825,"gu":94.95,"fc":100,"t":[0,0]},{"s":10775,"gu":94.51,"fc":100,"t":[0,0]},{"s":9969,"gu":94.94,"fc":100,"t":[0,0]},{"s":9608,"gu":94.19,"fc":100,"t":[0,0]},{"s":10816,"gu":97.44,"fc":100,"t":[0,0]},{"s":12259,"gu":97.29,"fc":100,"t":[0,0]},{"s":8734,"gu":97.04,"fc":100,"t":[0,0]},{"s":9366,"gu":94.6,"fc":100,"t":[0,0]},{"s":10842,"gu":95.1,"fc":100,"t":[0,0]},{"s":9644,"gu":94.54,"fc":100,"t":[0,0]},{"s":11981,"gu":95.08,"fc":100,"t":[0,0]},{"s":9944,"gu":94.7,"fc":100,"t":[0,0]}]},{"id":250,"score":204464,"gu":96.142,"fc":100,"git":"f44dd55","rounds":[{"s":11688,"gu":97.4,"fc":100,"t":[0,0]},{"s":9941,"gu":97.46,"fc":100,"t":[0,0]},{"s":10515,"gu":97.36,"fc":100,"t":[0,0]},{"s":10229,"gu":97.41,"fc":100,"t":[0,0]},{"s":10534,"gu":97.53,"fc":100,"t":[0,0]},{"s":7848,"gu":96.88,"fc":100,"t":[0,0]},{"s":9904,"gu":97.09,"fc":100,"t":[0,0]},{"s":9389,"gu":97.8,"fc":100,"t":[0,0]},{"s":10809,"gu":94.81,"fc":100,"t":[0,0]},{"s":10769,"gu":94.46,"fc":100,"t":[0,0]},{"s":9983,"gu":95.07,"fc":100,"t":[0,0]},{"s":9599,"gu":94.1,"fc":100,"t":[0,0]},{"s":10508,"gu":97.29,"fc":100,"t":[0,0]},{"s":12262,"gu":97.31,"fc":100,"t":[0,0]},{"s":8431,"gu":96.9,"fc":100,"t":[0,0]},{"s":9366,"gu":94.6,"fc":100,"t":[0,0]},{"s":10841,"gu":95.09,"fc":100,"t":[0,0]},{"s":9637,"gu":94.48,"fc":100,"t":[0,0]},{"s":11975,"gu":95.03,"fc":100,"t":[0,0]},{"s":10236,"gu":94.77,"fc":100,"t":[0,0]}]},{"id":71,"score":204191,"gu":96.1455,"fc":100,"git":"f44dd55","rounds":[{"s":11693,"gu":97.44,"fc":100,"t":[0,0]},{"s":9941,"gu":97.46,"fc":100,"t":[0,0]},{"s":10520,"gu":97.4,"fc":100,"t":[0,0]},{"s":10229,"gu":97.41,"fc":100,"t":[0,0]},{"s":10534,"gu":97.53,"fc":100,"t":[0,0]},{"s":7848,"gu":96.88,"fc":100,"t":[0,0]},{"s":9616,"gu":97.13,"fc":100,"t":[0,0]},{"s":9685,"gu":97.82,"fc":100,"t":[0,0]},{"s":10819,"gu":94.9,"fc":100,"t":[0,0]},{"s":10767,"gu":94.44,"fc":100,"t":[0,0]},{"s":9983,"gu":95.07,"fc":100,"t":[0,0]},{"s":9602,"gu":94.13,"fc":100,"t":[0,0]},{"s":10509,"gu":97.3,"fc":100,"t":[0,0]},{"s":12262,"gu":97.31,"fc":100,"t":[0,0]},{"s":8430,"gu":96.89,"fc":100,"t":[0,0]},{"s":9361,"gu":94.55,"fc":100,"t":[0,0]},{"s":11140,"gu":95.21,"fc":100,"t":[0,0]},{"s":9629,"gu":94.4,"fc":100,"t":[0,0]},{"s":11683,"gu":94.98,"fc":100,"t":[0,0]},{"s":9940,"gu":94.66,"fc":100,"t":[0,0]}]},{"id":311,"score":204191,"gu":96.1455,"fc":100,"git":"f44dd55","rounds":[{"s":11693,"gu":97.44,"fc":100,"t":[0,0]},{"s":9941,"gu":97.46,"fc":100,"t":[0,0]},{"s":10520,"gu":97.4,"fc":100,"t":[0,0]},{"s":10229,"gu":97.41,"fc":100,"t":[0,0]},{"s":10534,"gu":97.53,"fc":100,"t":[0,0]},{"s":7848,"gu":96.88,"fc":100,"t":[0,0]},{"s":9616,"gu":97.13,"fc":100,"t":[0,0]},{"s":9685,"gu":97.82,"fc":100,"t":[0,0]},{"s":10819,"gu":94.9,"fc":100,"t":[0,0]},{"s":10767,"gu":94.44,"fc":100,"t":[0,0]},{"s":9983,"gu":95.07,"fc":100,"t":[0,0]},{"s":9602,"gu":94.13,"fc":100,"t":[0,0]},{"s":10509,"gu":97.3,"fc":100,"t":[0,0]},{"s":12262,"gu":97.31,"fc":100,"t":[0,0]},{"s":8430,"gu":96.89,"fc":100,"t":[0,0]},{"s":9361,"gu":94.55,"fc":100,"t":[0,0]},{"s":11140,"gu":95.21,"fc":100,"t":[0,0]},{"s":9629,"gu":94.4,"fc":100,"t":[0,0]},{"s":11683,"gu":94.98,"fc":100,"t":[0,0]},{"s":9940,"gu":94.66,"fc":100,"t":[0,0]}]},{"id":163,"score":204191,"gu":96.1455,"fc":100,"git":"f44dd55","rounds":[{"s":11693,"gu":97.44,"fc":100,"t":[0,0]},{"s":9941,"gu":97.46,"fc":100,"t":[0,0]},{"s":10520,"gu":97.4,"fc":100,"t":[0,0]},{"s":10229,"gu":97.41,"fc":100,"t":[0,0]},{"s":10534,"gu":97.53,"fc":100,"t":[0,0]},{"s":7848,"gu":96.88,"fc":100,"t":[0,0]},{"s":9616,"gu":97.13,"fc":100,"t":[0,0]},{"s":9685,"gu":97.82,"fc":100,"t":[0,0]},{"s":10819,"gu":94.9,"fc":100,"t":[0,0]},{"s":10767,"gu":94.44,"fc":100,"t":[0,0]},{"s":9983,"gu":95.07,"fc":100,"t":[0,0]},{"s":9602,"gu":94.13,"fc":100,"t":[0,0]},{"s":10509,"gu":97.3,"fc":100,"t":[0,0]},{"s":12262,"gu":97.31,"fc":100,"t":[0,0]},{"s":8430,"gu":96.89,"fc":100,"t":[0,0]},{"s":9361,"gu":94.55,"fc":100,"t":[0,0]},{"s":11140,"gu":95.21,"fc":100,"t":[0,0]},{"s":9629,"gu":94.4,"fc":100,"t":[0,0]},{"s":11683,"gu":94.98,"fc":100,"t":[0,0]},{"s":9940,"gu":94.66,"fc":100,"t":[0,0]}]},{"id":286,"score":204191,"gu":96.1455,"fc":100,"git":"f44dd55","rounds":[{"s":11693,"gu":97.44,"fc":100,"t":[0,0]},{"s":9941,"gu":97.46,"fc":100,"t":[0,0]},{"s":10520,"gu":97.4,"fc":100,"t":[0,0]},{"s":10229,"gu":97.41,"fc":100,"t":[0,0]},{"s":10534,"gu":97.53,"fc":100,"t":[0,0]},{"s":7848,"gu":96.88,"fc":100,"t":[0,0]},{"s":9616,"gu":97.13,"fc":100,"t":[0,0]},{"s":9685,"gu":97.82,"fc":100,"t":[0,0]},{"s":10819,"gu":94.9,"fc":100,"t":[0,0]},{"s":10767,"gu":94.44,"fc":100,"t":[0,0]},{"s":9983,"gu":95.07,"fc":100,"t":[0,0]},{"s":9602,"gu":94.13,"fc":100,"t":[0,0]},{"s":10509,"gu":97.3,"fc":100,"t":[0,0]},{"s":12262,"gu":97.31,"fc":100,"t":[0,0]},{"s":8430,"gu":96.89,"fc":100,"t":[0,0]},{"s":9361,"gu":94.55,"fc":100,"t":[0,0]},{"s":11140,"gu":95.21,"fc":100,"t":[0,0]},{"s":9629,"gu":94.4,"fc":100,"t":[0,0]},{"s":11683,"gu":94.98,"fc":100,"t":[0,0]},{"s":9940,"gu":94.66,"fc":100,"t":[0,0]}]},{"id":68,"score":204188,"gu":96.146,"fc":100,"git":"f44dd55","rounds":[{"s":11693,"gu":97.44,"fc":100,"t":[0,0]},{"s":9956,"gu":97.6,"fc":100,"t":[0,0]},{"s":10234,"gu":97.46,"fc":100,"t":[0,0]},{"s":10227,"gu":97.4,"fc":100,"t":[0,0]},{"s":10534,"gu":97.53,"fc":100,"t":[0,0]},{"s":7834,"gu":96.71,"fc":100,"t":[0,0]},{"s":9605,"gu":97.02,"fc":100,"t":[0,0]},{"s":9688,"gu":97.85,"fc":100,"t":[0,0]},{"s":10814,"gu":94.85,"fc":100,"t":[0,0]},{"s":10767,"gu":94.44,"fc":100,"t":[0,0]},{"s":9980,"gu":95.04,"fc":100,"t":[0,0]},{"s":9591,"gu":94.02,"fc":100,"t":[0,0]},{"s":10223,"gu":97.36,"fc":100,"t":[0,0]},{"s":12547,"gu":97.26,"fc":100,"t":[0,0]},{"s":8432,"gu":96.91,"fc":100,"t":[0,0]},{"s":9372,"gu":94.66,"fc":100,"t":[0,0]},{"s":11144,"gu":95.24,"fc":100,"t":[0,0]},{"s":9622,"gu":94.33,"fc":100,"t":[0,0]},{"s":11687,"gu":95.01,"fc":100,"t":[0,0]},{"s":10238,"gu":94.79,"fc":100,"t":[0,0]}]},{"id":48,"score":204141,"gu":96.1255,"fc":100,"git":"f44dd55","rounds":[{"s":11683,"gu":97.35,"fc":100,"t":[0,0]},{"s":9934,"gu":97.39,"fc":100,"t":[0,0]},{"s":9938,"gu":97.43,"fc":100,"t":[0,0]},{"s":10214,"gu":97.27,"fc":100,"t":[0,0]},{"s":10825,"gu":97.52,"fc":100,"t":[0,0]},{"s":8140,"gu":96.9,"fc":100,"t":[0,0]},{"s":9590,"gu":96.86,"fc":100,"t":[0,0]},{"s":9389,"gu":97.8,"fc":100,"t":[0,0]},{"s":10819,"gu":94.9,"fc":100,"t":[0,0]},{"s":11069,"gu":94.6,"fc":100,"t":[0,0]},{"s":9660,"gu":94.7,"fc":100,"t":[0,0]},{"s":9607,"gu":94.18,"fc":100,"t":[0,0]},{"s":10513,"gu":97.34,"fc":100,"t":[0,0]},{"s":12251,"gu":97.23,"fc":100,"t":[0,0]},{"s":8725,"gu":96.94,"fc":100,"t":[0,0]},{"s":9368,"gu":94.62,"fc":100,"t":[0,0]},{"s":10546,"gu":95,"fc":100,"t":[0,0]},{"s":9654,"gu":94.64,"fc":100,"t":[0,0]},{"s":11981,"gu":95.08,"fc":100,"t":[0,0]},{"s":10235,"gu":94.76,"fc":100,"t":[0,0]}]},{"id":63,"score":203341,"gu":96.1605,"fc":100,"git":"f44dd55","rounds":[{"s":11432,"gu":97.7,"fc":100,"t":[0,0]},{"s":9372,"gu":97.62,"fc":100,"t":[0,0]},{"s":10527,"gu":97.47,"fc":100,"t":[0,0]},{"s":10220,"gu":97.33,"fc":100,"t":[0,0]},{"s":10537,"gu":97.56,"fc":100,"t":[0,0]},{"s":7842,"gu":96.81,"fc":100,"t":[0,0]},{"s":9917,"gu":97.22,"fc":100,"t":[0,0]},{"s":9986,"gu":97.9,"fc":100,"t":[0,0]},{"s":10813,"gu":94.85,"fc":100,"t":[0,0]},{"s":10765,"gu":94.42,"fc":100,"t":[0,0]},{"s":9684,"gu":94.94,"fc":100,"t":[0,0]},{"s":9592,"gu":94.03,"fc":100,"t":[0,0]},{"s":10219,"gu":97.32,"fc":100,"t":[0,0]},{"s":11676,"gu":97.3,"fc":100,"t":[0,0]},{"s":8426,"gu":96.85,"fc":100,"t":[0,0]},{"s":9357,"gu":94.51,"fc":100,"t":[0,0]},{"s":11430,"gu":95.25,"fc":100,"t":[0,0]},{"s":9625,"gu":94.36,"fc":100,"t":[0,0]},{"s":11681,"gu":94.96,"fc":100,"t":[0,0]},{"s":10240,"gu":94.81,"fc":100,"t":[0,0]}]},{"id":85,"score":187554,"gu":95.341,"fc":100,"git":"f44dd55","rounds":[{"s":10120,"gu":96.38,"fc":100,"t":[0,0]},{"s":9327,"gu":97.15,"fc":100,"t":[0,0]},{"s":10164,"gu":96.8,"fc":100,"t":[0,0]},{"s":10176,"gu":96.91,"fc":100,"t":[0,0]},{"s":9509,"gu":96.05,"fc":100,"t":[0,0]},{"s":7518,"gu":96.38,"fc":100,"t":[0,0]},{"s":9267,"gu":96.53,"fc":100,"t":[0,0]},{"s":9025,"gu":97.04,"fc":100,"t":[0,0]},{"s":9847,"gu":93.78,"fc":100,"t":[0,0]},{"s":10408,"gu":93.76,"fc":100,"t":[0,0]},{"s":9304,"gu":96.91,"fc":100,"t":[0,0]},{"s":8679,"gu":96.43,"fc":100,"t":[0,0]},{"s":9293,"gu":93.86,"fc":100,"t":[0,0]},{"s":10687,"gu":93.74,"fc":100,"t":[0,0]},{"s":8380,"gu":96.32,"fc":100,"t":[0,0]},{"s":8690,"gu":93.44,"fc":100,"t":[0,0]},{"s":9293,"gu":93.86,"fc":100,"t":[0,0]},{"s":9275,"gu":93.68,"fc":100,"t":[0,0]},{"s":9560,"gu":93.72,"fc":100,"t":[0,0]},{"s":9032,"gu":94.08,"fc":100,"t":[0,0]}]},{"id":56,"score":187523,"gu":95.3135,"fc":100,"git":"f44dd55","rounds":[{"s":10110,"gu":96.28,"fc":100,"t":[0,0]},{"s":9618,"gu":97.15,"fc":100,"t":[0,0]},{"s":9589,"gu":96.85,"fc":100,"t":[0,0]},{"s":10454,"gu":96.79,"fc":100,"t":[0,0]},{"s":10123,"gu":96.4,"fc":100,"t":[0,0]},{"s":6618,"gu":95.91,"fc":100,"t":[0,0]},{"s":8893,"gu":95.62,"fc":100,"t":[0,0]},{"s":8708,"gu":96.75,"fc":100,"t":[0,0]},{"s":9864,"gu":93.94,"fc":100,"t":[0,0]},{"s":10681,"gu":93.69,"fc":100,"t":[0,0]},{"s":9623,"gu":94.34,"fc":100,"t":[0,0]},{"s":8361,"gu":96.1,"fc":100,"t":[0,0]},{"s":10212,"gu":97.25,"fc":100,"t":[0,0]},{"s":10105,"gu":93.56,"fc":100,"t":[0,0]},{"s":7802,"gu":96.32,"fc":100,"t":[0,0]},{"s":8092,"gu":93.01,"fc":100,"t":[0,0]},{"s":9336,"gu":94.3,"fc":100,"t":[0,0]},{"s":9592,"gu":94.03,"fc":100,"t":[0,0]},{"s":10733,"gu":94.14,"fc":100,"t":[0,0]},{"s":9009,"gu":93.84,"fc":100,"t":[0,0]}]},{"id":315,"score":187251,"gu":95.0555,"fc":100,"git":"f44dd55","rounds":[{"s":9819,"gu":96.26,"fc":100,"t":[0,0]},{"s":8705,"gu":96.72,"fc":100,"t":[0,0]},{"s":8975,"gu":96.5,"fc":100,"t":[0,0]},{"s":8675,"gu":93.27,"fc":100,"t":[0,0]},{"s":10406,"gu":96.35,"fc":100,"t":[0,0]},{"s":6620,"gu":95.94,"fc":100,"t":[0,0]},{"s":9854,"gu":96.6,"fc":100,"t":[0,0]},{"s":8973,"gu":96.48,"fc":100,"t":[0,0]},{"s":10158,"gu":94.05,"fc":100,"t":[0,0]},{"s":10405,"gu":93.73,"fc":100,"t":[0,0]},{"s":9649,"gu":94.59,"fc":100,"t":[0,0]},{"s":8680,"gu":93.33,"fc":100,"t":[0,0]},{"s":9925,"gu":94.52,"fc":100,"t":[0,0]},{"s":10121,"gu":93.71,"fc":100,"t":[0,0]},{"s":8108,"gu":96.52,"fc":100,"t":[0,0]},{"s":8981,"gu":93.55,"fc":100,"t":[0,0]},{"s":9897,"gu":94.25,"fc":100,"t":[0,0]},{"s":8676,"gu":96.4,"fc":100,"t":[0,0]},{"s":10417,"gu":93.84,"fc":100,"t":[0,0]},{"s":10207,"gu":94.5,"fc":100,"t":[0,0]}]},{"id":354,"score":9779,"gu":28.310000000000002,"fc":100,"git":"f44dd55","rounds":[{"s":828,"gu":46,"fc":100,"t":[0,0]},{"s":64,"gu":5.33,"fc":100,"t":[0,0]},{"s":492,"gu":32.8,"fc":100,"t":[0,0]},{"s":332,"gu":22.13,"fc":100,"t":[0,0]},{"s":37,"gu":3.08,"fc":100,"t":[0,0]},{"s":15,"gu":1.25,"fc":100,"t":[0,0]},{"s":833,"gu":46.27,"fc":100,"t":[0,0]},{"s":313,"gu":20.86,"fc":100,"t":[0,0]},{"s":500,"gu":33.33,"fc":100,"t":[0,0]},{"s":160,"gu":13.33,"fc":100,"t":[0,0]},{"s":669,"gu":44.6,"fc":100,"t":[0,0]},{"s":1179,"gu":56.14,"fc":100,"t":[0,0]},{"s":100,"gu":8.33,"fc":100,"t":[0,0]},{"s":951,"gu":45.28,"fc":100,"t":[0,0]},{"s":142,"gu":11.83,"fc":100,"t":[0,0]},{"s":668,"gu":37.11,"fc":100,"t":[0,0]},{"s":450,"gu":30,"fc":100,"t":[0,0]},{"s":510,"gu":34,"fc":100,"t":[0,0]},{"s":1283,"gu":53.45,"fc":100,"t":[0,0]},{"s":253,"gu":21.08,"fc":100,"t":[0,0]}]},{"id":247,"score":5012,"gu":16.651,"fc":100,"git":"f44dd55","rounds":[{"s":621,"gu":34.5,"fc":100,"t":[0,0]},{"s":535,"gu":29.72,"fc":100,"t":[0,0]},{"s":0,"gu":0,"fc":100,"t":[0,0]},{"s":226,"gu":18.83,"fc":100,"t":[0,0]},{"s":477,"gu":31.8,"fc":100,"t":[0,0]},{"s":0,"gu":0,"fc":100,"t":[0,0]},{"s":155,"gu":12.91,"fc":100,"t":[0,0]},{"s":178,"gu":14.83,"fc":100,"t":[0,0]},{"s":0,"gu":0,"fc":100,"t":[0,0]},{"s":102,"gu":8.5,"fc":100,"t":[0,0]},{"s":496,"gu":33.06,"fc":100,"t":[0,0]},{"s":672,"gu":44.8,"fc":100,"t":[0,0]},{"s":0,"gu":0,"fc":100,"t":[0,0]},{"s":0,"gu":0,"fc":100,"t":[0,0]},{"s":0,"gu":0,"fc":100,"t":[0,0]},{"s":272,"gu":22.66,"fc":100,"t":[0,0]},{"s":731,"gu":40.61,"fc":100,"t":[0,0]},{"s":14,"gu":1.16,"fc":100,"t":[0,0]},{"s":247,"gu":20.58,"fc":100,"t":[0,0]},{"s":286,"gu":19.06,"fc":100,"t":[0,0]}]},{"id":284,"score":4930,"gu":16.3425,"fc":100,"git":"f44dd55","rounds":[{"s":174,"gu":14.49,"fc":100,"t":[0,0]},{"s":522,"gu":34.79,"fc":100,"t":[0,0]},{"s":0,"gu":0,"fc":100,"t":[0,0]},{"s":342,"gu":22.8,"fc":100,"t":[0,0]},{"s":485,"gu":32.33,"fc":100,"t":[0,0]},{"s":206,"gu":17.16,"fc":100,"t":[0,0]},{"s":0,"gu":0,"fc":100,"t":[0,0]},{"s":0,"gu":0,"fc":100,"t":[0,0]},{"s":0,"gu":0,"fc":100,"t":[0,0]},{"s":651,"gu":36.16,"fc":100,"t":[0,0]},{"s":282,"gu":23.5,"fc":100,"t":[0,0]},{"s":171,"gu":14.24,"fc":100,"t":[0,0]},{"s":0,"gu":0,"fc":100,"t":[0,0]},{"s":0,"gu":0,"fc":100,"t":[0,0]},{"s":256,"gu":21.33,"fc":100,"t":[0,0]},{"s":915,"gu":43.57,"fc":100,"t":[0,0]},{"s":402,"gu":26.8,"fc":100,"t":[0,0]},{"s":0,"gu":0,"fc":100,"t":[0,0]},{"s":239,"gu":15.93,"fc":100,"t":[0,0]},{"s":285,"gu":23.75,"fc":100,"t":[0,0]}]},{"id":105,"score":4930,"gu":16.3425,"fc":100,"git":"f44dd55","rounds":[{"s":174,"gu":14.49,"fc":100,"t":[0,0]},{"s":522,"gu":34.79,"fc":100,"t":[0,0]},{"s":0,"gu":0,"fc":100,"t":[0,0]},{"s":342,"gu":22.8,"fc":100,"t":[0,0]},{"s":485,"gu":32.33,"fc":100,"t":[0,0]},{"s":206,"gu":17.16,"fc":100,"t":[0,0]},{"s":0,"gu":0,"fc":100,"t":[0,0]},{"s":0,"gu":0,"fc":100,"t":[0,0]},{"s":0,"gu":0,"fc":100,"t":[0,0]},{"s":651,"gu":36.16,"fc":100,"t":[0,0]},{"s":282,"gu":23.5,"fc":100,"t":[0,0]},{"s":171,"gu":14.24,"fc":100,"t":[0,0]},{"s":0,"gu":0,"fc":100,"t":[0,0]},{"s":0,"gu":0,"fc":100,"t":[0,0]},{"s":256,"gu":21.33,"fc":100,"t":[0,0]},{"s":915,"gu":43.57,"fc":100,"t":[0,0]},{"s":402,"gu":26.8,"fc":100,"t":[0,0]},{"s":0,"gu":0,"fc":100,"t":[0,0]},{"s":239,"gu":15.93,"fc":100,"t":[0,0]},{"s":285,"gu":23.75,"fc":100,"t":[0,0]}]},{"id":120,"score":4930,"gu":16.3425,"fc":100,"git":"f44dd55","rounds":[{"s":174,"gu":14.49,"fc":100,"t":[0,0]},{"s":522,"gu":34.79,"fc":100,"t":[0,0]},{"s":0,"gu":0,"fc":100,"t":[0,0]},{"s":342,"gu":22.8,"fc":100,"t":[0,0]},{"s":485,"gu":32.33,"fc":100,"t":[0,0]},{"s":206,"gu":17.16,"fc":100,"t":[0,0]},{"s":0,"gu":0,"fc":100,"t":[0,0]},{"s":0,"gu":0,"fc":100,"t":[0,0]},{"s":0,"gu":0,"fc":100,"t":[0,0]},{"s":651,"gu":36.16,"fc":100,"t":[0,0]},{"s":282,"gu":23.5,"fc":100,"t":[0,0]},{"s":171,"gu":14.24,"fc":100,"t":[0,0]},{"s":0,"gu":0,"fc":100,"t":[0,0]},{"s":0,"gu":0,"fc":100,"t":[0,0]},{"s":256,"gu":21.33,"fc":100,"t":[0,0]},{"s":915,"gu":43.57,"fc":100,"t":[0,0]},{"s":402,"gu":26.8,"fc":100,"t":[0,0]},{"s":0,"gu":0,"fc":100,"t":[0,0]},{"s":239,"gu":15.93,"fc":100,"t":[0,0]},{"s":285,"gu":23.75,"fc":100,"t":[0,0]}]},{"id":87,"score":4930,"gu":16.3425,"fc":100,"git":"f44dd55","rounds":[{"s":174,"gu":14.49,"fc":100,"t":[0,0]},{"s":522,"gu":34.79,"fc":100,"t":[0,0]},{"s":0,"gu":0,"fc":100,"t":[0,0]},{"s":342,"gu":22.8,"fc":100,"t":[0,0]},{"s":485,"gu":32.33,"fc":100,"t":[0,0]},{"s":206,"gu":17.16,"fc":100,"t":[0,0]},{"s":0,"gu":0,"fc":100,"t":[0,0]},{"s":0,"gu":0,"fc":100,"t":[0,0]},{"s":0,"gu":0,"fc":100,"t":[0,0]},{"s":651,"gu":36.16,"fc":100,"t":[0,0]},{"s":282,"gu":23.5,"fc":100,"t":[0,0]},{"s":171,"gu":14.24,"fc":100,"t":[0,0]},{"s":0,"gu":0,"fc":100,"t":[0,0]},{"s":0,"gu":0,"fc":100,"t":[0,0]},{"s":256,"gu":21.33,"fc":100,"t":[0,0]},{"s":915,"gu":43.57,"fc":100,"t":[0,0]},{"s":402,"gu":26.8,"fc":100,"t":[0,0]},{"s":0,"gu":0,"fc":100,"t":[0,0]},{"s":239,"gu":15.93,"fc":100,"t":[0,0]},{"s":285,"gu":23.75,"fc":100,"t":[0,0]}]},{"id":292,"score":4194,"gu":14.8405,"fc":100,"git":"f44dd55","rounds":[{"s":244,"gu":16.26,"fc":100,"t":[0,0]},{"s":331,"gu":22.06,"fc":100,"t":[0,0]},{"s":0,"gu":0,"fc":100,"t":[0,0]},{"s":0,"gu":0,"fc":100,"t":[0,0]},{"s":233,"gu":15.53,"fc":100,"t":[0,0]},{"s":0,"gu":0,"fc":100,"t":[0,0]},{"s":158,"gu":13.16,"fc":100,"t":[0,0]},{"s":181,"gu":15.08,"fc":100,"t":[0,0]},{"s":279,"gu":18.6,"fc":100,"t":[0,0]},{"s":24,"gu":2,"fc":100,"t":[0,0]},{"s":381,"gu":25.4,"fc":100,"t":[0,0]},{"s":162,"gu":13.5,"fc":100,"t":[0,0]},{"s":179,"gu":14.91,"fc":100,"t":[0,0]},{"s":147,"gu":12.25,"fc":100,"t":[0,0]},{"s":851,"gu":47.27,"fc":100,"t":[0,0]},{"s":249,"gu":20.75,"fc":100,"t":[0,0]},{"s":343,"gu":28.58,"fc":100,"t":[0,0]},{"s":0,"gu":0,"fc":100,"t":[0,0]},{"s":272,"gu":18.13,"fc":100,"t":[0,0]},{"s":160,"gu":13.33,"fc":100,"t":[0,0]}]},{"id":76,"score":0,"gu":0,"fc":100,"git":"f44dd55","rounds":[{"s":0,"gu":0,"fc":100,"disqualified":"terminated_unexpectedly","t":[0,0]},{"s":0,"gu":0,"fc":100,"disqualified":"terminated_unexpectedly","t":[0,0]},{"s":0,"gu":0,"fc":100,"disqualified":"terminated_unexpectedly","t":[0,0]},{"s":0,"gu":0,"fc":100,"disqualified":"terminated_unexpectedly","t":[0,0]},{"s":0,"gu":0,"fc":100,"disqualified":"terminated_unexpectedly","t":[0,0]},{"s":0,"gu":0,"fc":100,"disqualified":"terminated_unexpectedly","t":[0,0]},{"s":0,"gu":0,"fc":100,"disqualified":"terminated_unexpectedly","t":[0,0]},{"s":0,"gu":0,"fc":100,"disqualified":"terminated_unexpectedly","t":[0,0]},{"s":0,"gu":0,"fc":100,"disqualified":"terminated_unexpectedly","t":[0,0]},{"s":0,"gu":0,"fc":100,"disqualified":"terminated_unexpectedly","t":[0,0]},{"s":0,"gu":0,"fc":100,"disqualified":"terminated_unexpectedly","t":[0,0]},{"s":0,"gu":0,"fc":100,"disqualified":"terminated_unexpectedly","t":[0,0]},{"s":0,"gu":0,"fc":100,"disqualified":"terminated_unexpectedly","t":[0,0]},{"s":0,"gu":0,"fc":100,"disqualified":"terminated_unexpectedly","t":[0,0]},{"s":0,"gu":0,"fc":100,"disqualified":"terminated_unexpectedly","t":[0,0]},{"s":0,"gu":0,"fc":100,"disqualified":"terminated_unexpectedly","t":[0,0]},{"s":0,"gu":0,"fc":100,"disqualified":"terminated_unexpectedly","t":[0,0]},{"s":0,"gu":0,"fc":100,"disqualified":"terminated_unexpectedly","t":[0,0]},{"s":0,"gu":0,"fc":100,"disqualified":"terminated_unexpectedly","t":[0,0]},{"s":0,"gu":0,"fc":100,"disqualified":"terminated_unexpectedly","t":[0,0]}]},{"id":207,"score":0,"gu":0,"fc":0,"git":"","rounds":[{"s":0,"gu":0,"fc":0,"disqualified":"non deterministic","t":[0,0]},{"s":0,"gu":0,"fc":0,"disqualified":"non deterministic","t":[0,0]},{"s":0,"gu":0,"fc":0,"disqualified":"non deterministic","t":[0,0]},{"s":0,"gu":0,"fc":0,"disqualified":"non deterministic","t":[0,0]},{"s":0,"gu":0,"fc":0,"disqualified":"non deterministic","t":[0,0]},{"s":0,"gu":0,"fc":0,"disqualified":"non deterministic","t":[0,0]},{"s":0,"gu":0,"fc":0,"disqualified":"non deterministic","t":[0,0]},{"s":0,"gu":0,"fc":0,"disqualified":"non deterministic","t":[0,0]},{"s":0,"gu":0,"fc":0,"disqualified":"non deterministic","t":[0,0]},{"s":0,"gu":0,"fc":0,"disqualified":"non deterministic","t":[0,0]},{"s":0,"gu":0,"fc":0,"disqualified":"non deterministic","t":[0,0]},{"s":0,"gu":0,"fc":0,"disqualified":"non deterministic","t":[0,0]},{"s":0,"gu":0,"fc":0,"disqualified":"non deterministic","t":[0,0]},{"s":0,"gu":0,"fc":0,"disqualified":"non deterministic","t":[0,0]},{"s":0,"gu":0,"fc":0,"disqualified":"non deterministic","t":[0,0]},{"s":0,"gu":0,"fc":0,"disqualified":"non deterministic","t":[0,0]},{"s":0,"gu":0,"fc":0,"disqualified":"non deterministic","t":[0,0]},{"s":0,"gu":0,"fc":0,"disqualified":"non deterministic","t":[0,0]},{"s":0,"gu":0,"fc":0,"disqualified":"non deterministic","t":[0,0]},{"s":0,"gu":0,"fc":0,"disqualified":"non deterministic","t":[0,0]}]}]}